rotavision/__init__.py
rotavision/client.py
rotavision/dastavez.py
rotavision/gati.py
rotavision/guardian.py
rotavision/orchestrate.py
rotavision/sankalp.py
rotavision/vishwas.py
rotavision-0.1.0.dist-info/METADATA
rotavision-0.1.0.dist-info/WHEEL
rotavision-0.1.0.dist-info/RECORD
