Metadata-Version: 2.4
Name: rotavision
Version: 0.1.0
Summary: Official Python SDK for Rotavision AI Trust Infrastructure
Project-URL: Homepage, https://rotavision.com
Project-URL: Documentation, https://rotavision.com/docs
Project-URL: Repository, https://github.com/rotavision/rotavision-python
Project-URL: Changelog, https://github.com/rotavision/rotavision-python/blob/main/CHANGELOG.md
Author-email: Rotavision <developers@rotavision.com>
License-Expression: Apache-2.0
Keywords: ai,fairness,governance,india,llm,monitoring,rotavision,trust
Classifier: Development Status :: 3 - Alpha
Classifier: Intended Audience :: Developers
Classifier: License :: OSI Approved :: Apache Software License
Classifier: Operating System :: OS Independent
Classifier: Programming Language :: Python :: 3
Classifier: Programming Language :: Python :: 3.8
Classifier: Programming Language :: Python :: 3.9
Classifier: Programming Language :: Python :: 3.10
Classifier: Programming Language :: Python :: 3.11
Classifier: Programming Language :: Python :: 3.12
Classifier: Topic :: Scientific/Engineering :: Artificial Intelligence
Requires-Python: >=3.8
Requires-Dist: httpx>=0.24.0
Requires-Dist: pydantic>=2.0.0
Provides-Extra: dev
Requires-Dist: black>=23.0.0; extra == 'dev'
Requires-Dist: mypy>=1.0.0; extra == 'dev'
Requires-Dist: pytest-asyncio>=0.21.0; extra == 'dev'
Requires-Dist: pytest>=7.0.0; extra == 'dev'
Requires-Dist: ruff>=0.1.0; extra == 'dev'
